version/__init__.py
version/regress.py
version_regress-5.0.0.dist-info/LICENSE
version_regress-5.0.0.dist-info/METADATA
version_regress-5.0.0.dist-info/WHEEL
version_regress-5.0.0.dist-info/top_level.txt
version_regress-5.0.0.dist-info/RECORD
