Metadata-Version: 2.1
Name: version-regress
Version: 5.0.0
Summary: A small package to test PyPi versions
Home-page: https://github.com/thibaultduponchelle/version-regress
Author: Thibault Duponchelle
Author-email: thibault.duponchelle@gmail.com
License: UNKNOWN
Project-URL: Bug Tracker, https://github.com/thibaultduponchelle/version-regress/issues
Platform: UNKNOWN
Classifier: Programming Language :: Python :: 3
Classifier: License :: OSI Approved :: MIT License
Classifier: Operating System :: OS Independent
Requires-Python: >=3.6
License-File: LICENSE
